ovos_simple_listener/__init__.py
ovos_simple_listener/__main__.py
ovos_simple_listener/version.py
ovos_simple_listener-0.1.0.dist-info/licenses/LICENSE
ovos_simple_listener-0.1.0.dist-info/METADATA
ovos_simple_listener-0.1.0.dist-info/WHEEL
ovos_simple_listener-0.1.0.dist-info/entry_points.txt
ovos_simple_listener-0.1.0.dist-info/top_level.txt
ovos_simple_listener-0.1.0.dist-info/RECORD
