Metadata-Version: 2.4
Name: ovos-simple-listener
Version: 0.1.0
Summary: ovos-core listener daemon client
Home-page: https://github.com/OpenVoiceOS/ovos-simple-listener
License: Apache-2.0
Classifier: Development Status :: 4 - Beta
Classifier: Programming Language :: Python :: 3
Classifier: License :: OSI Approved :: Apache Software License
License-File: LICENSE
Requires-Dist: ovos-plugin-manager<3.0.0,>=2.1.1
Requires-Dist: ovos-utils<1.0.0,>=0.0.38
Requires-Dist: ovos-config<3.0.0,>=0.4.3
Requires-Dist: ovos_bus_client<2.0.0,>=0.0.10
Requires-Dist: SpeechRecognition~=3.9
Dynamic: classifier
Dynamic: description
Dynamic: description-content-type
Dynamic: home-page
Dynamic: license
Dynamic: license-file
Dynamic: requires-dist
Dynamic: summary
